{"indexCode":"DJI","keyStatisticsList":[{"code":"AAPL","week52Rank":-1,"companyName":"Apple Inc","marketcap":"2097644439480","week52high":"181.66","week52low":"128.49","week52change":"-0.2466946485384356","week52highSplitAdjustOnly":"182.94","week52lowSplitAdjustOnly":"129.04","sharesOutstanding":"15908118000","Float":"0","avg10Volume":"76924085","avg30Volume":"81651918","day200MovingAvg":"148.75","day50MovingAvg":"143.05","employees":"147000","ttmEPS":"6.11","ttmDividendRate":"1.073484249163088","dividendYield":"0.008141090923427028","nextDividendDate":"","exDividendDate":"2022-12-23","nextEarningsDate":"2023-01-26","peRatio":"21.01784955843011","maxChangePercent":"50.11645216312607","year5ChangePercent":"2.173388397133217","year2ChangePercent":"0.01243702021342119","year1ChangePercent":"-0.2466946485384356","ytdChangePercent":"-0.25216704816393565","month6ChangePercent":"-0.06516215388454671","month3ChangePercent":"-0.12088351673261476","month1ChangePercent":"-0.10859208792664844","day5ChangePercent":"-0.01846354484577961","day30ChangePercent":"-0.10859208792664844","beta":"1.2980899408840487"},{"code":"AMGN","week52Rank":-1,"companyName":"AMGEN Inc.","marketcap":"140822224048","week52high":"294.64","week52low":"209.61","week52change":"0.21656935003058475","week52highSplitAdjustOnly":"296.67","week52lowSplitAdjustOnly":"214.39","sharesOutstanding":"533579206","Float":"0","avg10Volume":"1958336","avg30Volume":"3028328","day200MovingAvg":"251.36","day50MovingAvg":"279.74","employees":"22000","ttmEPS":"12.48","ttmDividendRate":"7.675417928450783","dividendYield":"0.02908236559734307","nextDividendDate":"2023-02-14","exDividendDate":"2022-11-16","nextEarningsDate":"2023-02-06","peRatio":"20.60310520080761","maxChangePercent":"4.220938352492468","year5ChangePercent":"0.74725105214411","year2ChangePercent":"0.268543654974583","year1ChangePercent":"0.21656935003058475","ytdChangePercent":"0.21018865865407327","month6ChangePercent":"0.09137223766044732","month3ChangePercent":"0.17080580292382064","month1ChangePercent":"-0.06985268203284689","day5ChangePercent":"-0.01305112000299169","day30ChangePercent":"-0.06985268203284689","beta":"0.34366406428476753"},{"code":"AXP","week52Rank":-1,"companyName":"American Express Co.","marketcap":"109858150966","week52high":"197.49","week52low":"130.65","week52change":"-0.09296016909364502","week52highSplitAdjustOnly":"199.55","week52lowSplitAdjustOnly":"130.65","sharesOutstanding":"747232696","Float":"0","avg10Volume":"2166950","avg30Volume":"2747629","day200MovingAvg":"148.87","day50MovingAvg":"152.3","employees":"0","ttmEPS":"9.96","ttmDividendRate":"1.979673626662107","dividendYield":"0.013465335509876934","nextDividendDate":"2023-01-05","exDividendDate":"2022-10-13","nextEarningsDate":"2023-01-27","peRatio":"14.583585685108192","maxChangePercent":"1.9335472336621653","year5ChangePercent":"0.5930962218415203","year2ChangePercent":"0.28387730597096383","year1ChangePercent":"-0.09296016909364502","ytdChangePercent":"-0.0896893166973467","month6ChangePercent":"0.013571740776028518","month3ChangePercent":"0.05219764883708633","month1ChangePercent":"-0.04625364904313978","day5ChangePercent":"0.004921394395078549","day30ChangePercent":"-0.04625364904313978","beta":"1.12857270964512"},{"code":"BA","week52Rank":-1,"companyName":"Boeing Co.","marketcap":"112265939611","week52high":"229.67","week52low":"113.02","week52change":"-0.07423366957203015","week52highSplitAdjustOnly":"229.67","week52lowSplitAdjustOnly":"113.02","sharesOutstanding":"593811169","Float":"0","avg10Volume":"6569941","avg30Volume":"7046033","day200MovingAvg":"154.99","day50MovingAvg":"179","employees":"141014","ttmEPS":"-14.25","ttmDividendRate":"0","dividendYield":"0","nextDividendDate":"","exDividendDate":"","nextEarningsDate":"2023-01-25","peRatio":"-13.29535049871388","maxChangePercent":"1.8640941427411435","year5ChangePercent":"-0.3277345586253442","year2ChangePercent":"-0.1293575869214828","year1ChangePercent":"-0.07423366957203015","ytdChangePercent":"-0.06089807272004766","month6ChangePercent":"0.3358298593937681","month3ChangePercent":"0.44034740210269696","month1ChangePercent":"0.05999102937878442","day5ChangePercent":"0.0236058473199785","day30ChangePercent":"0.05999102937878442","beta":"1.2238447076907983"},{"code":"CAT","week52Rank":-1,"companyName":"Caterpillar Inc.","marketcap":"124830591984","week52high":"241.91","week52low":"159.53","week52change":"0.19063278208595769","week52highSplitAdjustOnly":"241.91","week52lowSplitAdjustOnly":"160.6","sharesOutstanding":"520409355","Float":"0","avg10Volume":"2901190","avg30Volume":"3057034","day200MovingAvg":"197.13","day50MovingAvg":"233.44","employees":"102300","ttmEPS":"13.76","ttmDividendRate":"4.576788950494725","dividendYield":"0.01908028911699973","nextDividendDate":"2023-01-19","exDividendDate":"2022-10-21","nextEarningsDate":"2023-01-26","peRatio":"16.935367247842898","maxChangePercent":"4.600775193798449","year5ChangePercent":"0.7335943806882774","year2ChangePercent":"0.38845395793598647","year1ChangePercent":"0.19063278208595769","ytdChangePercent":"0.1875228660159145","month6ChangePercent":"0.31088966929096","month3ChangePercent":"0.4702574283642551","month1ChangePercent":"0.017691981332202067","day5ChangePercent":"0.030723616363011352","day30ChangePercent":"0.017691981332202067","beta":"0.7820079462252092"},{"code":"CRM","week52Rank":-1,"companyName":"Salesforce Inc","marketcap":"129440000000","week52high":"260.78","week52low":"126.34","week52change":"-0.4886624002528245","week52highSplitAdjustOnly":"260.78","week52lowSplitAdjustOnly":"126.34","sharesOutstanding":"1000000000","Float":"0","avg10Volume":"8600875","avg30Volume":"12834676","day200MovingAvg":"159.88","day50MovingAvg":"142.52","employees":"49000","ttmEPS":"0.2775","ttmDividendRate":"0","dividendYield":"0","nextDividendDate":"","exDividendDate":"","nextEarningsDate":"2023-02-28","peRatio":"465.61151079136687","maxChangePercent":"13.20466392318244","year5ChangePercent":"0.26122965994348624","year2ChangePercent":"-0.4266985561165737","year1ChangePercent":"-0.4886624002528245","ytdChangePercent":"-0.4906543894856963","month6ChangePercent":"-0.3037865748709122","month3ChangePercent":"-0.11951567920549622","month1ChangePercent":"-0.15591783501793277","day5ChangePercent":"0.009121384579402704","day30ChangePercent":"-0.15591783501793277","beta":"1.4967542802397158"},{"code":"CSCO","week52Rank":-1,"companyName":"Cisco Systems, Inc.","marketcap":"195087921049","week52high":"62.89","week52low":"38.6","week52change":"-0.22072081683164255","week52highSplitAdjustOnly":"64.29","week52lowSplitAdjustOnly":"38.6","sharesOutstanding":"4108844167","Float":"0","avg10Volume":"16269100","avg30Volume":"19415912","day200MovingAvg":"44.47","day50MovingAvg":"47.52","employees":"75900","ttmEPS":"2.76","ttmDividendRate":"1.4971066708780498","dividendYield":"0.03153131151807182","nextDividendDate":"2023-01-04","exDividendDate":"2022-10-04","nextEarningsDate":"2023-02-15","peRatio":"16.961217270836375","maxChangePercent":"1.345363116349374","year5ChangePercent":"0.40920733571367074","year2ChangePercent":"0.1216127790153525","year1ChangePercent":"-0.22072081683164255","ytdChangePercent":"-0.2341243725239699","month6ChangePercent":"0.08664556541958746","month3ChangePercent":"0.17857905266868213","month1ChangePercent":"-0.0190082644628099","day5ChangePercent":"-0.006902321690023139","day30ChangePercent":"-0.0190082644628099","beta":"0.8454332905998431"},{"code":"CVX","week52Rank":-1,"companyName":"Chevron Corp.","marketcap":"343027478060","week52high":"188.22","week52low":"111.4","week52change":"0.5788185560129047","week52highSplitAdjustOnly":"189.68","week52lowSplitAdjustOnly":"115.41","sharesOutstanding":"1933638546","Float":"0","avg10Volume":"6129206","avg30Volume":"8404893","day200MovingAvg":"160.58","day50MovingAvg":"178.18","employees":"44679","ttmEPS":"17.61","ttmDividendRate":"5.610529513098271","dividendYield":"0.03162643468488315","nextDividendDate":"","exDividendDate":"2022-11-17","nextEarningsDate":"2023-01-27","peRatio":"10.039730677566071","maxChangePercent":"3.126166735281052","year5ChangePercent":"0.7427901146272551","year2ChangePercent":"1.235174643493424","year1ChangePercent":"0.5788185560129047","ytdChangePercent":"0.5661720952981288","month6ChangePercent":"0.2460910391022526","month3ChangePercent":"0.2348712608425385","month1ChangePercent":"-0.03429504627109403","day5ChangePercent":"0.05144618302513049","day30ChangePercent":"-0.03429504627109403","beta":"0.5541207550550595"},{"code":"DIS","week52Rank":-1,"companyName":"Walt Disney Co (The)","marketcap":"160494330864","week52high":"160.32","week52low":"84.69","week52change":"-0.4271301178155308","week52highSplitAdjustOnly":"160.32","week52lowSplitAdjustOnly":"84.69","sharesOutstanding":"1823591988","Float":"0","avg10Volume":"14361499","avg30Volume":"14172828","day200MovingAvg":"101.21","day50MovingAvg":"93.59","employees":"0","ttmEPS":"1.72","ttmDividendRate":"0","dividendYield":"0","nextDividendDate":"","exDividendDate":"","nextEarningsDate":"2023-02-08","peRatio":"51.03158374050239","maxChangePercent":"2.0213046433549158","year5ChangePercent":"-0.16721942504927512","year2ChangePercent":"-0.4934093133022506","year1ChangePercent":"-0.4271301178155308","ytdChangePercent":"-0.4317903027955322","month6ChangePercent":"-0.0999181836776436","month3ChangePercent":"-0.11547738693467335","month1ChangePercent":"-0.10984120562354605","day5ChangePercent":"-0.022979573712255678","day30ChangePercent":"-0.10984120562354605","beta":"1.1429451479824198"},{"code":"DOW","week52Rank":-1,"companyName":"Dow Inc","marketcap":"35793196421","week52high":"69.21","week52low":"42.31","week52change":"-0.03075624262728716","week52highSplitAdjustOnly":"71.86","week52lowSplitAdjustOnly":"42.91","sharesOutstanding":"703759269","Float":"0","avg10Volume":"3699140","avg30Volume":"4827014","day200MovingAvg":"49.39","day50MovingAvg":"50.31","employees":"0","ttmEPS":"7.78","ttmDividendRate":"2.7456491289142138","dividendYield":"0.05398445003763692","nextDividendDate":"","exDividendDate":"2022-11-29","nextEarningsDate":"2023-01-26","peRatio":"6.274004631260298","maxChangePercent":"0.02128514056224895","year5ChangePercent":"0.02128514056224895","year2ChangePercent":"0.019471382239629964","year1ChangePercent":"-0.03075624262728716","ytdChangePercent":"-0.05775554629243662","month6ChangePercent":"-0.016519608696240695","month3ChangePercent":"0.1749268847111658","month1ChangePercent":"0.0003737141283608469","day5ChangePercent":"0.02128514056224895","day30ChangePercent":"0.0003737141283608469","beta":"0.7686173286087945"},{"code":"GS","week52Rank":-1,"companyName":"Goldman Sachs Group, Inc.","marketcap":"117001636500","week52high":"404.51","week52low":"273.96","week52change":"-0.08459622721492155","week52highSplitAdjustOnly":"412.66","week52lowSplitAdjustOnly":"277.84","sharesOutstanding":"338634588","Float":"0","avg10Volume":"1556818","avg30Volume":"2248442","day200MovingAvg":"328.32","day50MovingAvg":"367.8","employees":"40900","ttmEPS":"37.5","ttmDividendRate":"8.927871933409001","dividendYield":"0.02583969185670169","nextDividendDate":"","exDividendDate":"2022-11-30","nextEarningsDate":"2023-01-17","peRatio":"8.739291641759785","maxChangePercent":"1.1086480752963923","year5ChangePercent":"0.4592328331822053","year2ChangePercent":"0.4001194625966176","year1ChangePercent":"-0.08459622721492155","ytdChangePercent":"-0.0786380344278067","month6ChangePercent":"0.15739554346941298","month3ChangePercent":"0.1516900186865049","month1ChangePercent":"-0.10565262948636178","day5ChangePercent":"-0.0024252923343439647","day30ChangePercent":"-0.10565262948636178","beta":"0.9638445441026402"},{"code":"HD","week52Rank":-1,"companyName":"Home Depot, Inc.","marketcap":"326292329177","week52high":"407.59","week52low":"261.21","week52change":"-0.17710018501239522","week52highSplitAdjustOnly":"417.84","week52lowSplitAdjustOnly":"264.51","sharesOutstanding":"1023726443","Float":"0","avg10Volume":"2674586","avg30Volume":"4688034","day200MovingAvg":"294.65","day50MovingAvg":"316.49","employees":"400000","ttmEPS":"16.58","ttmDividendRate":"7.529462513236031","dividendYield":"0.02362332542664961","nextDividendDate":"","exDividendDate":"2022-11-30","nextEarningsDate":"2023-02-21","peRatio":"19.08700375416145","maxChangePercent":"9.859588212646637","year5ChangePercent":"0.906504534326114","year2ChangePercent":"0.23126667143108248","year1ChangePercent":"-0.17710018501239522","ytdChangePercent":"-0.21267253125546529","month6ChangePercent":"0.14046101489687637","month3ChangePercent":"0.18350292060434303","month1ChangePercent":"-0.017530816019984075","day5ChangePercent":"-0.014257437990969124","day30ChangePercent":"-0.017530816019984075","beta":"0.9328371664810856"},{"code":"HON","week52Rank":-1,"companyName":"Honeywell International Inc","marketcap":"143789555758","week52high":"220.96","week52low":"164.89","week52change":"0.06898440733269218","week52highSplitAdjustOnly":"221.89","week52lowSplitAdjustOnly":"166.63","sharesOutstanding":"672322232","Float":"0","avg10Volume":"2222390","avg30Volume":"2970950","day200MovingAvg":"189.97","day50MovingAvg":"214.08","employees":"113000","ttmEPS":"7.81","ttmDividendRate":"3.921572380263705","dividendYield":"0.018336243420132348","nextDividendDate":"","exDividendDate":"2022-11-09","nextEarningsDate":"2023-02-03","peRatio":"26.75154525727256","maxChangePercent":"5.947034022179057","year5ChangePercent":"0.6179609017368852","year2ChangePercent":"0.06488652811739604","year1ChangePercent":"0.06898440733269218","ytdChangePercent":"0.05211736960326818","month6ChangePercent":"0.2057668433568658","month3ChangePercent":"0.26026131551081333","month1ChangePercent":"-0.028084526244035457","day5ChangePercent":"0.019691046057022987","day30ChangePercent":"-0.028084526244035457","beta":"0.7833752389888435"},{"code":"IBM","week52Rank":-1,"companyName":"International Business Machines Corp.","marketcap":"128069499319","week52high":"153.21","week52low":"114.18","week52change":"0.13813861106111647","week52highSplitAdjustOnly":"153.21","week52lowSplitAdjustOnly":"115.55","sharesOutstanding":"904126363","Float":"0","avg10Volume":"3932715","avg30Volume":"4430991","day200MovingAvg":"133.08","day50MovingAvg":"145","employees":"352600","ttmEPS":"1.44","ttmDividendRate":"6.472157910111976","dividendYield":"0.04569119597678769","nextDividendDate":"","exDividendDate":"2022-11-09","nextEarningsDate":"2023-01-25","peRatio":"101.48137822420762","maxChangePercent":"1.307266300718323","year5ChangePercent":"0.18044224291526323","year2ChangePercent":"0.2523495368119151","year1ChangePercent":"0.13813861106111647","ytdChangePercent":"0.11233788058210648","month6ChangePercent":"0.021715327677413576","month3ChangePercent":"0.1681106212715706","month1ChangePercent":"-0.04529217496798543","day5ChangePercent":"0.010630707762557146","day30ChangePercent":"-0.04529217496798543","beta":"0.5361349364162075"},{"code":"INTC","week52Rank":-1,"companyName":"Intel Corp.","marketcap":"107673430000","week52high":"54.13","week52low":"24.26","week52change":"-0.4713401092577283","week52highSplitAdjustOnly":"56.28","week52lowSplitAdjustOnly":"24.59","sharesOutstanding":"4127000000","Float":"0","avg10Volume":"33741173","avg30Volume":"38278294","day200MovingAvg":"31.38","day50MovingAvg":"28.66","employees":"110600","ttmEPS":"3.24","ttmDividendRate":"1.4354129308056534","dividendYield":"0.05501774361079545","nextDividendDate":"","exDividendDate":"2022-11-04","nextEarningsDate":"2023-01-25","peRatio":"8.095137959551913","maxChangePercent":"0.9830803493383398","year5ChangePercent":"-0.35831060324706143","year2ChangePercent":"-0.4087989032528523","year1ChangePercent":"-0.4713401092577283","ytdChangePercent":"-0.4732910727984818","month6ChangePercent":"-0.3082272959880365","month3ChangePercent":"-0.03915914456069802","month1ChangePercent":"-0.11077027948193596","day5ChangePercent":"-0.03083209509658258","day30ChangePercent":"-0.11077027948193596","beta":"1.1865018552085618"},{"code":"JNJ","week52Rank":-1,"companyName":"Johnson \u0026 Johnson","marketcap":"464018550570","week52high":"183.08","week52low":"152.71","week52change":"0.08257402285922022","week52highSplitAdjustOnly":"186.69","week52lowSplitAdjustOnly":"155.72","sharesOutstanding":"2614483607","Float":"0","avg10Volume":"5355095","avg30Volume":"7160895","day200MovingAvg":"169.82","day50MovingAvg":"175.74","employees":"0","ttmEPS":"7.18","ttmDividendRate":"4.407505678082418","dividendYield":"0.02483381608114953","nextDividendDate":"","exDividendDate":"2022-11-21","nextEarningsDate":"2023-01-24","peRatio":"24.22187976041969","maxChangePercent":"2.9800147108950323","year5ChangePercent":"0.44566183340352006","year2ChangePercent":"0.22472216375863008","year1ChangePercent":"0.08257402285922022","ytdChangePercent":"0.0647283826783065","month6ChangePercent":"-0.01351826808758283","month3ChangePercent":"0.07141046104214399","month1ChangePercent":"0.0013540961408258223","day5ChangePercent":"0.010303409802470576","day30ChangePercent":"0.0013540961408258223","beta":"0.3046154498449318"},{"code":"JPM","week52Rank":-1,"companyName":"JPMorgan Chase \u0026 Co.","marketcap":"385071137697","week52high":"167.07","week52low":"101.28","week52change":"-0.14640616709840515","week52highSplitAdjustOnly":"169.81","week52lowSplitAdjustOnly":"101.28","sharesOutstanding":"2933204888","Float":"0","avg10Volume":"7872365","avg30Volume":"10226466","day200MovingAvg":"119.18","day50MovingAvg":"133.13","employees":"256981","ttmEPS":"11.85","ttmDividendRate":"3.9661044763029594","dividendYield":"0.03021103348798719","nextDividendDate":"2023-01-05","exDividendDate":"2022-10-05","nextEarningsDate":"2023-01-13","peRatio":"10.932688027273864","maxChangePercent":"2.9015575916619363","year5ChangePercent":"0.3923948597635218","year2ChangePercent":"0.10510073690218236","year1ChangePercent":"-0.14640616709840515","ytdChangePercent":"-0.15228189080915489","month6ChangePercent":"0.1290018808098059","month3ChangePercent":"0.21362050508356112","month1ChangePercent":"-0.03992979376919703","day5ChangePercent":"0.015391754969448668","day30ChangePercent":"-0.03992979376919703","beta":"0.8882831997952515"},{"code":"KO","week52Rank":-1,"companyName":"Coca-Cola Co","marketcap":"275990436508","week52high":"65.77","week52low":"53.63","week52change":"0.12861867119387416","week52highSplitAdjustOnly":"67.2","week52lowSplitAdjustOnly":"54.02","sharesOutstanding":"4324513264","Float":"0","avg10Volume":"9549772","avg30Volume":"13517968","day200MovingAvg":"60.6","day50MovingAvg":"62.22","employees":"86200","ttmEPS":"2.28","ttmDividendRate":"1.7412687201210972","dividendYield":"0.02728406017112343","nextDividendDate":"","exDividendDate":"2022-11-30","nextEarningsDate":"2023-02-09","peRatio":"27.807600655766247","maxChangePercent":"3.0433094063012778","year5ChangePercent":"0.6290170252954539","year2ChangePercent":"0.268330878948132","year1ChangePercent":"0.12861867119387416","ytdChangePercent":"0.10974706391739676","month6ChangePercent":"0.026986144859437067","month3ChangePercent":"0.09680291060076684","month1ChangePercent":"0.02524558824710632","day5ChangePercent":"0.017051792828685297","day30ChangePercent":"0.02524558824710632","beta":"0.48854642661816033"},{"code":"MCD","week52Rank":-1,"companyName":"McDonald`s Corp","marketcap":"195974660782","week52high":"280.09","week52low":"214.09","week52change":"0.0286244142699581","week52highSplitAdjustOnly":"281.67","week52lowSplitAdjustOnly":"217.68","sharesOutstanding":"732423892","Float":"0","avg10Volume":"1989812","avg30Volume":"2908171","day200MovingAvg":"255.85","day50MovingAvg":"271.56","employees":"0","ttmEPS":"7.94","ttmDividendRate":"5.614350645059032","dividendYield":"0.02098273590110637","nextDividendDate":"","exDividendDate":"2022-11-30","nextEarningsDate":"2023-01-26","peRatio":"33.14413827331214","maxChangePercent":"7.925247673371359","year5ChangePercent":"0.7457143323166255","year2ChangePercent":"0.3237435271034224","year1ChangePercent":"0.0286244142699581","ytdChangePercent":"0.0204895008613728","month6ChangePercent":"0.09136651062508938","month3ChangePercent":"0.09403097485163923","month1ChangePercent":"-0.02153844128517568","day5ChangePercent":"0.005448669773034709","day30ChangePercent":"-0.02153844128517568","beta":"0.4875429055285207"},{"code":"MMM","week52Rank":-1,"companyName":"3M Co.","marketcap":"66406533808","week52high":"174.39","week52low":"105.83","week52change":"-0.2842542488095231","week52highSplitAdjustOnly":"181.78","week52lowSplitAdjustOnly":"107.07","sharesOutstanding":"552742915","Float":"0","avg10Volume":"2544037","avg30Volume":"3085022","day200MovingAvg":"125.71","day50MovingAvg":"125.64","employees":"96163","ttmEPS":"11.45","ttmDividendRate":"5.863760260960179","dividendYield":"0.04880772649375877","nextDividendDate":"","exDividendDate":"2022-11-17","nextEarningsDate":"2023-01-24","peRatio":"10.099853050661595","maxChangePercent":"1.3249468304360192","year5ChangePercent":"-0.39415088840051593","year2ChangePercent":"-0.2596312946592264","year1ChangePercent":"-0.2842542488095231","ytdChangePercent":"-0.294972497824297","month6ChangePercent":"-0.08587689697283274","month3ChangePercent":"0.07572999481565112","month1ChangePercent":"-0.06897086174829503","day5ChangePercent":"-0.012737283260744523","day30ChangePercent":"-0.06897086174829503","beta":"0.6819374086959694"},{"code":"MRK","week52Rank":-1,"companyName":"Merck \u0026 Co Inc","marketcap":"283609393652","week52high":"112.17","week52low":"70.61","week52change":"0.5245722447711234","week52highSplitAdjustOnly":"112.17","week52lowSplitAdjustOnly":"72.88","sharesOutstanding":"2535395974","Float":"0","avg10Volume":"6906847","avg30Volume":"10370284","day200MovingAvg":"93.61","day50MovingAvg":"106.4","employees":"71000","ttmEPS":"6.08","ttmDividendRate":"2.76989191221934","dividendYield":"0.024762130450736095","nextDividendDate":"","exDividendDate":"2022-12-14","nextEarningsDate":"2023-02-02","peRatio":"18.58515030482569","maxChangePercent":"3.214944854534287","year5ChangePercent":"1.318971575702419","year2ChangePercent":"0.4929935013540514","year1ChangePercent":"0.5245722447711234","ytdChangePercent":"0.5064690901793998","month6ChangePercent":"0.21882256031188607","month3ChangePercent":"0.2975473501545087","month1ChangePercent":"0.04745281499432541","day5ChangePercent":"0.024358974358974272","day30ChangePercent":"0.04745281499432541","beta":"0.2883697923569978"},{"code":"MSFT","week52Rank":-1,"companyName":"Microsoft Corporation","marketcap":"1780090838005","week52high":"341.1","week52low":"212.83","week52change":"-0.28002943456087925","week52highSplitAdjustOnly":"344.3","week52lowSplitAdjustOnly":"213.43","sharesOutstanding":"7456502484","Float":"0","avg10Volume":"25679298","avg30Volume":"30293619","day200MovingAvg":"251.95","day50MovingAvg":"244.13","employees":"166475","ttmEPS":"9.28","ttmDividendRate":"2.530720170399952","dividendYield":"0.01060076308130504","nextDividendDate":"2023-02-15","exDividendDate":"2022-11-16","nextEarningsDate":"2023-01-24","peRatio":"25.50675375783175","maxChangePercent":"9.42024949585774","year5ChangePercent":"1.9646325410426448","year2ChangePercent":"0.09084993810764286","year1ChangePercent":"-0.28002943456087925","ytdChangePercent":"-0.2835188937265212","month6ChangePercent":"-0.10380682199981006","month3ChangePercent":"0.006232207691925007","month1ChangePercent":"-0.035395369509879315","day5ChangePercent":"-0.02435735011647389","day30ChangePercent":"-0.035395369509879315","beta":"1.2787547820797593"},{"code":"NKE","week52Rank":-1,"companyName":"Nike, Inc.","marketcap":"181350000000","week52high":"168.31","week52low":"81.97","week52change":"-0.2907649976511356","week52highSplitAdjustOnly":"170.12","week52lowSplitAdjustOnly":"82.22","sharesOutstanding":"1560000000","Float":"0","avg10Volume":"16859964","avg30Volume":"10242592","day200MovingAvg":"103.85","day50MovingAvg":"106.63","employees":"75400","ttmEPS":"3.52","ttmDividendRate":"1.249708741675475","dividendYield":"0.010750182724090108","nextDividendDate":"","exDividendDate":"2022-12-02","nextEarningsDate":"2023-03-20","peRatio":"26.046032076462765","maxChangePercent":"10.13825812014947","year5ChangePercent":"0.924837775500168","year2ChangePercent":"-0.1639649850556495","year1ChangePercent":"-0.2907649976511356","ytdChangePercent":"-0.2950200214313914","month6ChangePercent":"0.035707635548515304","month3ChangePercent":"0.2018845549822121","month1ChangePercent":"0.10047919360671288","day5ChangePercent":"0.09721566776781489","day30ChangePercent":"0.10047919360671288","beta":"1.3358599298796952"},{"code":"PG","week52Rank":-1,"companyName":"Procter \u0026 Gamble Co.","marketcap":"364074928806","week52high":"162.68","week52low":"121.32","week52change":"-0.02305005284184125","week52highSplitAdjustOnly":"165.35","week52lowSplitAdjustOnly":"122.18","sharesOutstanding":"2385499468","Float":"0","avg10Volume":"5172115","avg30Volume":"7008922","day200MovingAvg":"139.73","day50MovingAvg":"146.77","employees":"0","ttmEPS":"5.66","ttmDividendRate":"3.574479587017307","dividendYield":"0.02342078093970192","nextDividendDate":"","exDividendDate":"2022-10-20","nextEarningsDate":"2023-01-19","peRatio":"25.48295155079163","maxChangePercent":"2.583571267563303","year5ChangePercent":"0.898147745094503","year2ChangePercent":"0.1642649538093024","year1ChangePercent":"-0.02305005284184125","ytdChangePercent":"-0.04383378671140725","month6ChangePercent":"0.07171246478418292","month3ChangePercent":"0.13367348985287195","month1ChangePercent":"0.04021264994547447","day5ChangePercent":"0.014490826907737286","day30ChangePercent":"0.04021264994547447","beta":"0.4728045741002902"},{"code":"TRV","week52Rank":-1,"companyName":"Travelers Companies Inc.","marketcap":"44404169037","week52high":"190.21","week52low":"148.91","week52change":"0.25144641526780465","week52highSplitAdjustOnly":"191.16","week52lowSplitAdjustOnly":"149.65","sharesOutstanding":"234347525","Float":"0","avg10Volume":"969527","avg30Volume":"1370228","day200MovingAvg":"168.88","day50MovingAvg":"185.24","employees":"30800","ttmEPS":"13.76","ttmDividendRate":"3.641635440177124","dividendYield":"0.01921910196420268","nextDividendDate":"","exDividendDate":"2022-12-08","nextEarningsDate":"2023-01-24","peRatio":"13.330582118583008","maxChangePercent":"2.5291488172844105","year5ChangePercent":"0.5843312747394984","year2ChangePercent":"0.4290950723824434","year1ChangePercent":"0.25144641526780465","ytdChangePercent":"0.2372062957267802","month6ChangePercent":"0.14867760824322265","month3ChangePercent":"0.22473435971950304","month1ChangePercent":"0.008002630127192045","day5ChangePercent":"0.03654266958424501","day30ChangePercent":"0.008002630127192045","beta":"0.44133407821223325"},{"code":"UNH","week52Rank":-1,"companyName":"Unitedhealth Group Inc","marketcap":"496429005976","week52high":"556.38","week52low":"440.1","week52change":"0.08626583468952131","week52highSplitAdjustOnly":"558.1","week52lowSplitAdjustOnly":"445.74","sharesOutstanding":"934349073","Float":"0","avg10Volume":"1844302","avg30Volume":"3150805","day200MovingAvg":"521.17","day50MovingAvg":"530.76","employees":"325000","ttmEPS":"20.41","ttmDividendRate":"6.370615305271219","dividendYield":"0.01199039224797429","nextDividendDate":"","exDividendDate":"2022-12-02","nextEarningsDate":"2023-01-13","peRatio":"25.54961430651724","maxChangePercent":"11.03990110833894","year5ChangePercent":"1.5983965852243855","year2ChangePercent":"0.6012216431184325","year1ChangePercent":"0.08626583468952131","ytdChangePercent":"0.07164193915737815","month6ChangePercent":"0.07864587319642857","month3ChangePercent":"0.03765080123961084","month1ChangePercent":"-0.00869044744852221","day5ChangePercent":"0.01453122016421604","day30ChangePercent":"-0.00869044744852221","beta":"0.5757666988186653"},{"code":"V","week52Rank":-1,"companyName":"Visa Inc","marketcap":"389104031561","week52high":"233.54","week52low":"173.81","week52change":"-0.04039631729999971","week52highSplitAdjustOnly":"235.85","week52lowSplitAdjustOnly":"174.6","sharesOutstanding":"1890414573","Float":"0","avg10Volume":"4588506","avg30Volume":"7802378","day200MovingAvg":"201.02","day50MovingAvg":"208.8","employees":"19500","ttmEPS":"6.79","ttmDividendRate":"1.5668118061697591","dividendYield":"0.007612164437495792","nextDividendDate":"","exDividendDate":"2022-11-09","nextEarningsDate":"2023-01-26","peRatio":"22.94781599967331","maxChangePercent":"9.61975667894623","year5ChangePercent":"0.8918720185299229","year2ChangePercent":"0.002137874657543337","year1ChangePercent":"-0.04039631729999971","ytdChangePercent":"-0.04079476605654009","month6ChangePercent":"0.007912280340936162","month3ChangePercent":"0.1239937135424234","month1ChangePercent":"-0.03723279854062389","day5ChangePercent":"-0.0051234955773598045","day30ChangePercent":"-0.03723279854062389","beta":"0.9794817715947344"},{"code":"VZ","week52Rank":-1,"companyName":"Verizon Communications Inc","marketcap":"161314988139","week52high":"53.91","week52low":"34.55","week52change":"-0.23097868523583187","week52highSplitAdjustOnly":"55.51","week52lowSplitAdjustOnly":"34.55","sharesOutstanding":"4199817447","Float":"0","avg10Volume":"23713456","avg30Volume":"25975290","day200MovingAvg":"41.61","day50MovingAvg":"37.95","employees":"135300","ttmEPS":"4.6","ttmDividendRate":"2.51758496947016","dividendYield":"0.06554503955923353","nextDividendDate":"2023-01-09","exDividendDate":"2022-10-06","nextEarningsDate":"2023-01-24","peRatio":"8.361755553559506","maxChangePercent":"1.1683781479871511","year5ChangePercent":"-0.08351010143188131","year2ChangePercent":"-0.2729454699638082","year1ChangePercent":"-0.23097868523583187","ytdChangePercent":"-0.2203231568691134","month6ChangePercent":"-0.223936928964266","month3ChangePercent":"-0.011719905829077226","month1ChangePercent":"-0.01563300871348039","day5ChangePercent":"0.0347521551724137","day30ChangePercent":"-0.01563300871348039","beta":"0.37109948692314076"},{"code":"WBA","week52Rank":-1,"companyName":"Walgreens Boots Alliance Inc","marketcap":"33311971305","week52high":"52.57","week52low":"30.04","week52change":"-0.1993599854089937","week52highSplitAdjustOnly":"55","week52lowSplitAdjustOnly":"30.39","sharesOutstanding":"862334230","Float":"0","avg10Volume":"5341851","avg30Volume":"5442857","day200MovingAvg":"37.14","day50MovingAvg":"40.13","employees":"450000","ttmEPS":"5.01","ttmDividendRate":"1.881811112496192","dividendYield":"0.04871372281895397","nextDividendDate":"","exDividendDate":"2022-11-14","nextEarningsDate":"2023-01-05","peRatio":"7.67910818462425","maxChangePercent":"-0.3672202738496365","year5ChangePercent":"-0.369091871198709","year2ChangePercent":"0.059014784537232856","year1ChangePercent":"-0.1993599854089937","ytdChangePercent":"-0.22514672668118885","month6ChangePercent":"-0.05043999803352828","month3ChangePercent":"0.19051654796428785","month1ChangePercent":"-0.07273163706192975","day5ChangePercent":"-0.01075544174135712","day30ChangePercent":"-0.07273163706192975","beta":"0.766108457350095"},{"code":"WMT","week52Rank":-1,"companyName":"Walmart Inc","marketcap":"387718943764","week52high":"158.89","week52low":"116.32","week52change":"0.04688519433311589","week52highSplitAdjustOnly":"160.77","week52lowSplitAdjustOnly":"117.27","sharesOutstanding":"2696800054","Float":"0","avg10Volume":"4562479","avg30Volume":"6650426","day200MovingAvg":"134.53","day50MovingAvg":"147","employees":"2","ttmEPS":"3.26","ttmDividendRate":"2.2268400398710835","dividendYield":"0.01548890616867972","nextDividendDate":"","exDividendDate":"2022-12-08","nextEarningsDate":"2023-02-21","peRatio":"43.23842352666221","maxChangePercent":"3.2570138426234365","year5ChangePercent":"0.5953651518631828","year2ChangePercent":"0.0338130277555464","year1ChangePercent":"0.04688519433311589","ytdChangePercent":"0.009260741252418605","month6ChangePercent":"0.17152009152475256","month3ChangePercent":"0.109580424707594","month1ChangePercent":"-0.057215608894974346","day5ChangePercent":"0.007145359019264497","day30ChangePercent":"-0.057215608894974346","beta":"0.4375298243937781"}],"businessDate":"2022-12-27","updatedTimeStamp":"2022-12-27T00:23:55.162587580Z"}